Downloader.py
Importer.py
MANIFEST.in
Parser.py
README.rst
Standardizer.py
Transformer.py
Updater.py
__init__.py
initial_importing.py
main.py
setup.py
./Downloader.py
./Importer.py
./Parser.py
./Standardizer.py
./Transformer.py
./Updater.py
./__init__.py
./initial_importing.py
./main.py
Qimport.egg-info/PKG-INFO
Qimport.egg-info/SOURCES.txt
Qimport.egg-info/dependency_links.txt
Qimport.egg-info/requires.txt
Qimport.egg-info/top_level.txt
Qimport.egg-info/zip-safe